langchain_sql_test/__init__.py
langchain_sql_test/chain.py
langchain_sql_test/database.py
langchain_sql_test/prompt.py
langchain_sql_test/tool.py
langchain_sql_test-0.0.3.dist-info/LICENSE
langchain_sql_test-0.0.3.dist-info/METADATA
langchain_sql_test-0.0.3.dist-info/WHEEL
langchain_sql_test-0.0.3.dist-info/RECORD
